customer_analyzer/__init__.py
customer_analyzer/analyzer.py
yet_anothersh_customer_analyzer-0.1.0.dist-info/METADATA
yet_anothersh_customer_analyzer-0.1.0.dist-info/WHEEL
yet_anothersh_customer_analyzer-0.1.0.dist-info/entry_points.txt
yet_anothersh_customer_analyzer-0.1.0.dist-info/top_level.txt
yet_anothersh_customer_analyzer-0.1.0.dist-info/RECORD
