Metadata-Version: 2.1
Name: yet_anothersh_customer_analyzer
Version: 0.1.0
Author-email: "v.lavrinov" <v.lavrinov@edu.centraluniversity.ru>
Requires-Dist: pandas
